eso_names/__init__.py
eso_names/main.py
eso_names/name_generator_v2.py
eso_names/name_recommender.py
eso_names/raw_model.py
eso_names/db/names.csv
eso_names/model/model_2.pth
eso_names-1.0.dist-info/METADATA
eso_names-1.0.dist-info/WHEEL
eso_names-1.0.dist-info/top_level.txt
eso_names-1.0.dist-info/RECORD
