Metadata-Version: 2.1
Name: eso-names
Version: 1.0
Requires-Dist: filelock (==3.13.1)
Requires-Dist: fsspec (==2023.12.2)
Requires-Dist: Jinja2 (==3.1.3)
Requires-Dist: Levenshtein (==0.23.0)
Requires-Dist: MarkupSafe (==2.1.4)
Requires-Dist: mpmath (==1.3.0)
Requires-Dist: networkx (==3.2.1)
Requires-Dist: numpy (==1.26.3)
Requires-Dist: pandas (==2.2.0)
Requires-Dist: python-dateutil (==2.8.2)
Requires-Dist: pytz (==2023.3.post1)
Requires-Dist: rapidfuzz (==3.6.1)
Requires-Dist: six (==1.16.0)
Requires-Dist: sympy (==1.12)
Requires-Dist: torch (==2.1.2)
Requires-Dist: typing-extensions (==4.9.0)
Requires-Dist: tzdata (==2023.4)
